packagetestbancolombia/__init__.py
packagetestbancolombia/functions.py
packagetestbancolombia-1.0.1.dist-info/METADATA
packagetestbancolombia-1.0.1.dist-info/WHEEL
packagetestbancolombia-1.0.1.dist-info/top_level.txt
packagetestbancolombia-1.0.1.dist-info/RECORD
