Metadata-Version: 2.1
Name: packagetestbancolombia
Version: 1.0.1
Summary: Testing installation of Package
Home-page: https://github.com/bancolombia/test-distribute-pypi
Author: ghoyos
Author-email: ghoyos@bancolombia.com.co
License: MIT
